pyca/__init__.py
pyca/celltype.py
pyca/observer.py
pyca/profiler.py
pyca/switch.py
pyca/universe1d.py
pyca/universe2d.py
pyca/rules/BaseRule.py
pyca/rules/Cyclic2D.py
pyca/rules/Rules.py
pyca/rules/__init__.py
tests/__init__.py
tests/test_music.py
tests/test_universe.py
pycax-1.0.0.dist-info/LICENCE.txt
pycax-1.0.0.dist-info/METADATA
pycax-1.0.0.dist-info/WHEEL
pycax-1.0.0.dist-info/top_level.txt
pycax-1.0.0.dist-info/RECORD
