Metadata-Version: 2.1
Name: pycax
Version: 1.0.0
Summary: Cellular Automata, CA, in Python.
Home-page: https://github.com/wangzhe3224/pyca
Author: Zhe Wang
Author-email: wangzhetju@gmail.com
License: UNKNOWN
Platform: UNKNOWN
Classifier: Programming Language :: Python :: 3
Classifier: License :: OSI Approved :: MIT License
Classifier: Operating System :: OS Independent
Requires-Python: >=3.6
